{"errors":[],"warnings":[],"namedChunkGroups":{"app":{"chunks":[11,0,3],"assets":["webpack-runtime-73b7a76d63c88895e1ff.js","webpack-runtime-73b7a76d63c88895e1ff.js.map","styles.63f4ea0bde0252adefd2.css","styles-58b94a828eedf37f351f.js","styles-58b94a828eedf37f351f.js.map","app-bb70c81f1b763220a3bb.js","app-bb70c81f1b763220a3bb.js.map"],"children":{},"childAssets":{}},"component---src-pages-404-js":{"chunks":[0,1,4],"assets":["styles.63f4ea0bde0252adefd2.css","styles-58b94a828eedf37f351f.js","styles-58b94a828eedf37f351f.js.map","1-4b86395ddd1b809362c8.js","1-4b86395ddd1b809362c8.js.map","component---src-pages-404-js-ae81e058e7bce8e6ee31.js","component---src-pages-404-js-ae81e058e7bce8e6ee31.js.map"],"children":{},"childAssets":{}},"component---src-pages-bios-js":{"chunks":[0,1,2,5],"assets":["styles.63f4ea0bde0252adefd2.css","styles-58b94a828eedf37f351f.js","styles-58b94a828eedf37f351f.js.map","1-4b86395ddd1b809362c8.js","1-4b86395ddd1b809362c8.js.map","2-e991d324acc63db01d3b.js","2-e991d324acc63db01d3b.js.map","component---src-pages-bios-js-f780c49c753990babe4d.js","component---src-pages-bios-js-f780c49c753990babe4d.js.map"],"children":{},"childAssets":{}},"component---src-pages-events-js":{"chunks":[0,1,2,6],"assets":["styles.63f4ea0bde0252adefd2.css","styles-58b94a828eedf37f351f.js","styles-58b94a828eedf37f351f.js.map","1-4b86395ddd1b809362c8.js","1-4b86395ddd1b809362c8.js.map","2-e991d324acc63db01d3b.js","2-e991d324acc63db01d3b.js.map","component---src-pages-events-js-9bdbfbff98a36417c772.js","component---src-pages-events-js-9bdbfbff98a36417c772.js.map"],"children":{},"childAssets":{}},"component---src-pages-index-js":{"chunks":[0,1,2,7],"assets":["styles.63f4ea0bde0252adefd2.css","styles-58b94a828eedf37f351f.js","styles-58b94a828eedf37f351f.js.map","1-4b86395ddd1b809362c8.js","1-4b86395ddd1b809362c8.js.map","2-e991d324acc63db01d3b.js","2-e991d324acc63db01d3b.js.map","component---src-pages-index-js-0e4042fcf8067913bfa2.js","component---src-pages-index-js-0e4042fcf8067913bfa2.js.map"],"children":{},"childAssets":{}},"component---src-pages-news-js":{"chunks":[0,1,2,8],"assets":["styles.63f4ea0bde0252adefd2.css","styles-58b94a828eedf37f351f.js","styles-58b94a828eedf37f351f.js.map","1-4b86395ddd1b809362c8.js","1-4b86395ddd1b809362c8.js.map","2-e991d324acc63db01d3b.js","2-e991d324acc63db01d3b.js.map","component---src-pages-news-js-c73daf087567010d0073.js","component---src-pages-news-js-c73daf087567010d0073.js.map"],"children":{},"childAssets":{}},"component---src-pages-tickets-js":{"chunks":[0,1,9],"assets":["styles.63f4ea0bde0252adefd2.css","styles-58b94a828eedf37f351f.js","styles-58b94a828eedf37f351f.js.map","1-4b86395ddd1b809362c8.js","1-4b86395ddd1b809362c8.js.map","component---src-pages-tickets-js-28cdfc07942f7bc8b810.js","component---src-pages-tickets-js-28cdfc07942f7bc8b810.js.map"],"children":{},"childAssets":{}},"pages-manifest":{"chunks":[10],"assets":["pages-manifest-20a4cb3018ac0cb58929.js","pages-manifest-20a4cb3018ac0cb58929.js.map"],"children":{},"childAssets":{}}},"assetsByChunkName":{"app":["webpack-runtime-73b7a76d63c88895e1ff.js","styles.63f4ea0bde0252adefd2.css","styles-58b94a828eedf37f351f.js","app-bb70c81f1b763220a3bb.js"],"component---src-pages-404-js":["styles.63f4ea0bde0252adefd2.css","styles-58b94a828eedf37f351f.js","1-4b86395ddd1b809362c8.js","component---src-pages-404-js-ae81e058e7bce8e6ee31.js"],"component---src-pages-bios-js":["styles.63f4ea0bde0252adefd2.css","styles-58b94a828eedf37f351f.js","1-4b86395ddd1b809362c8.js","2-e991d324acc63db01d3b.js","component---src-pages-bios-js-f780c49c753990babe4d.js"],"component---src-pages-events-js":["styles.63f4ea0bde0252adefd2.css","styles-58b94a828eedf37f351f.js","1-4b86395ddd1b809362c8.js","2-e991d324acc63db01d3b.js","component---src-pages-events-js-9bdbfbff98a36417c772.js"],"component---src-pages-index-js":["styles.63f4ea0bde0252adefd2.css","styles-58b94a828eedf37f351f.js","1-4b86395ddd1b809362c8.js","2-e991d324acc63db01d3b.js","component---src-pages-index-js-0e4042fcf8067913bfa2.js"],"component---src-pages-news-js":["styles.63f4ea0bde0252adefd2.css","styles-58b94a828eedf37f351f.js","1-4b86395ddd1b809362c8.js","2-e991d324acc63db01d3b.js","component---src-pages-news-js-c73daf087567010d0073.js"],"component---src-pages-tickets-js":["styles.63f4ea0bde0252adefd2.css","styles-58b94a828eedf37f351f.js","1-4b86395ddd1b809362c8.js","component---src-pages-tickets-js-28cdfc07942f7bc8b810.js"],"pages-manifest":["pages-manifest-20a4cb3018ac0cb58929.js"]}}